aiola_tts/__init__.py
aiola_tts/audio_converter.py
aiola_tts/client.py
aiola_tts-1.0.0.dist-info/METADATA
aiola_tts-1.0.0.dist-info/WHEEL
aiola_tts-1.0.0.dist-info/top_level.txt
aiola_tts-1.0.0.dist-info/RECORD
