Metadata-Version: 2.4
Name: aiola_tts
Version: 1.0.0
Summary: Aiola Text-To-Speech Python SDK
Author-email: "Gilad O." <gilad.or@aiola.com>, "Dor B." <dor.benatia@aiola.com>, "Ami V." <amichai.vaknin@aiola.com>
License-Expression: MIT
Project-URL: Homepage, https://aiola.ai/
Project-URL: Repository, https://github.com/aiola-lab/aiola-python-sdk.git
Requires-Python: >=3.8
Requires-Dist: websocket-client>=1.7.0
Requires-Dist: python-socketio>=5.8.0
Requires-Dist: websocket-client>=1.6.0
Requires-Dist: sounddevice>=0.4.6
Requires-Dist: python-dotenv>=1.0.0
Requires-Dist: pydantic>=2.0.0
Requires-Dist: requests>=2.31.0
Requires-Dist: numpy>=1.24.0
Requires-Dist: aiohttp>=3.8.0
Provides-Extra: dev
Requires-Dist: pytest>=8.0.0; extra == "dev"
Requires-Dist: pytest-cov>=4.1.0; extra == "dev"
